mypythonlib/__init__.py
mypythonlib/myfunctions.py
print_lib-0.1.0.dist-info/METADATA
print_lib-0.1.0.dist-info/WHEEL
print_lib-0.1.0.dist-info/top_level.txt
print_lib-0.1.0.dist-info/RECORD
